homeduino/__init__.py
homeduino/__main__.py
homeduino/_version.py
homeduino/homeduino.py
homeduino/py.typed
homeduino/task_helper.py
homeduino-0.0.21.dist-info/METADATA
homeduino-0.0.21.dist-info/WHEEL
homeduino-0.0.21.dist-info/licenses/LICENSE
homeduino-0.0.21.dist-info/RECORD
