Metadata-Version: 2.4
Name: homeduino
Version: 0.0.21
Summary: Homeduino library
Project-URL: Homepage, https://github.com/rrooggiieerr/homeduino.py
Project-URL: Issues, https://github.com/rrooggiieerr/homeduino.py/issues
Author-email: Rogier van Staveren <rogier@batoid.com>
License: GPLv3
License-File: LICENSE
Classifier: Development Status :: 4 - Beta
Classifier: Intended Audience :: Developers
Classifier: License :: OSI Approved :: GNU General Public License v3 (GPLv3)
Classifier: Operating System :: MacOS :: MacOS X
Classifier: Operating System :: POSIX
Classifier: Programming Language :: Python :: 3.11
Classifier: Programming Language :: Python :: 3.12
Classifier: Topic :: Home Automation
Classifier: Topic :: Software Development :: Libraries :: Python Modules
Requires-Python: >=3.11
Requires-Dist: pyserial-asyncio-fast>=0.16
Requires-Dist: rfcontrolpy==0.0.10
